patcherex/__init__.py
patcherex/patcherex.py
patcherex/allocation_management/__init__.py
patcherex/allocation_management/allocation_management.py
patcherex/assemblers/__init__.py
patcherex/assemblers/assembler.py
patcherex/assemblers/bcc.py
patcherex/assemblers/keystone.py
patcherex/assemblers/keystone_arm.py
patcherex/assemblers/keystone_sparc.py
patcherex/assemblers/ppc_vle.py
patcherex/assets/assets.py
patcherex/binary_analyzers/__init__.py
patcherex/binary_analyzers/angr.py
patcherex/binary_analyzers/binary_analyzer.py
patcherex/binary_analyzers/ida.py
patcherex/binfmt_tools/__init__.py
patcherex/binfmt_tools/binfmt_tool.py
patcherex/binfmt_tools/elf.py
patcherex/binfmt_tools/ihex.py
patcherex/compilers/__init__.py
patcherex/compilers/bcc.py
patcherex/compilers/clang.py
patcherex/compilers/clang_arm.py
patcherex/compilers/compiler.py
patcherex/compilers/ppc_vle.py
patcherex/disassemblers/__init__.py
patcherex/disassemblers/capstone.py
patcherex/disassemblers/capstone_arm.py
patcherex/disassemblers/disassembler.py
patcherex/disassemblers/ppc_vle.py
patcherex/patch_managers/__init__.py
patcherex/patch_managers/builtin.py
patcherex/patch_managers/imp.py
patcherex/patch_managers/patch_manager.py
patcherex/patches/__init__.py
patcherex/patches/data_patches.py
patcherex/patches/dummy_patches.py
patcherex/patches/function_patches.py
patcherex/patches/instruction_patches.py
patcherex/patches/patch.py
patcherex/patches/raw_patches.py
patcherex/targets/__init__.py
patcherex/targets/elf_aarch64_linux.py
patcherex/targets/elf_arm_linux.py
patcherex/targets/elf_arm_mimxrt1052.py
patcherex/targets/elf_leon3_bare.py
patcherex/targets/ihex_ppc_bare.py
patcherex/targets/target.py
patcherex/utils/__init__.py
patcherex/utils/utils.py
tests/aarch64.py
tests/arm.py
patcherex-2.0.2.dist-info/LICENSE
patcherex-2.0.2.dist-info/METADATA
patcherex-2.0.2.dist-info/WHEEL
patcherex-2.0.2.dist-info/top_level.txt
patcherex-2.0.2.dist-info/RECORD
