Metadata-Version: 2.1
Name: patcherex
Version: 2.0.2
License-File: LICENSE
Requires-Dist: angr
Requires-Dist: pyelftools
Requires-Dist: lief
Requires-Dist: keystone-engine
Requires-Dist: intelhex
Requires-Dist: requests
Provides-Extra: test
Requires-Dist: shellphish-qemu ; extra == 'test'
